[{"file":"lecture_7","reflabel":"Definition","label":"Definition","reftag":"","autoid":"Definition*-9.1","title":"","neu":true,"id":"Definition*-9.1","refnum":"??","cls":"Definition"},{"file":"lecture_7","reflabel":"Theorem","label":"Theorem","reftag":"","autoid":"Theorem*-9.2","title":"","neu":true,"id":"Theorem*-9.2","refnum":"??","cls":"Theorem"},{"file":"lecture_7","reflabel":"Lemma","label":"Lemma","reftag":"","autoid":"Lemma*-9.3","title":"","neu":true,"id":"Lemma*-9.3","refnum":"??","cls":"Lemma"},{"file":"lecture_7","reflabel":"Definition","label":"Definition","reftag":"","autoid":"Definition*-9.4","title":"","neu":true,"id":"Definition*-9.4","refnum":"??","cls":"Definition"}]