[{"reftag":"","neu":true,"reflabel":"Definition","file":"lecture_5","autoid":"Definition*-2.1","refnum":"??","title":"","label":"Definition","id":"Definition*-2.1","cls":"Definition"},{"reftag":"","neu":true,"reflabel":"Theorem","file":"lecture_5","autoid":"Theorem*-2.2","refnum":"??","title":"","label":"Theorem","id":"Theorem*-2.2","cls":"Theorem"},{"reftag":"","neu":true,"reflabel":"Theorem","file":"lecture_5","autoid":"Theorem*-2.3","refnum":"??","title":"","label":"Theorem","id":"Theorem*-2.3","cls":"Theorem"},{"reftag":"","neu":true,"reflabel":"Theorem","file":"lecture_5","autoid":"Theorem*-3.1","refnum":"??","title":"","label":"Theorem","id":"Theorem*-3.1","cls":"Theorem"},{"reftag":"","neu":true,"reflabel":"Theorem","file":"lecture_5","autoid":"Theorem*-3.2","refnum":"??","title":"","label":"Theorem","id":"Theorem*-3.2","cls":"Theorem"},{"reftag":"","neu":true,"reflabel":"Definition","file":"lecture_5","autoid":"Definition*-3.3","refnum":"??","title":"","label":"Definition","id":"Definition*-3.3","cls":"Definition"},{"reftag":"","neu":true,"reflabel":"Definition","file":"lecture_5","autoid":"Definition*-5.1","refnum":"??","title":"","label":"Definition","id":"Definition*-5.1","cls":"Definition"},{"reftag":"","neu":true,"reflabel":"Definition","file":"lecture_5","autoid":"Definition*-5.2","refnum":"??","title":"","label":"Definition","id":"Definition*-5.2","cls":"Definition"},{"reftag":"","neu":true,"reflabel":"Definition","file":"lecture_5","autoid":"Definition*-5.3","refnum":"??","title":"","label":"Definition","id":"Definition*-5.3","cls":"Definition"},{"reftag":"","neu":true,"reflabel":"Theorem","file":"lecture_5","autoid":"Theorem*-5.4","refnum":"??","title":"","label":"Theorem","id":"Theorem*-5.4","cls":"Theorem"},{"reftag":"","neu":true,"reflabel":"Definition","file":"lecture_5","autoid":"Definition*-2.2","refnum":"??","id":"Definition*-2.2","label":"Definition","title":"","cls":"Definition"},{"reftag":"","neu":true,"reflabel":"Definition","file":"lecture_5","autoid":"Definition*-2.3","refnum":"??","id":"Definition*-2.3","label":"Definition","title":"","cls":"Definition"},{"reftag":"","neu":true,"reflabel":"Theorem","file":"lecture_5","autoid":"Theorem*-2.4","refnum":"??","id":"Theorem*-2.4","label":"Theorem","title":"","cls":"Theorem"},{"reftag":"","neu":true,"reflabel":"Theorem","file":"lecture_5","autoid":"Theorem*-2.1","refnum":"??","id":"Theorem*-2.1","label":"Theorem","title":"","cls":"Theorem"},{"reftag":"","neu":true,"reflabel":"Definition","file":"lecture_5","autoid":"Definition*-4.1","refnum":"??","id":"Definition*-4.1","label":"Definition","title":"","cls":"Definition"},{"reftag":"","neu":true,"reflabel":"Definition","file":"lecture_5","autoid":"Definition*-4.2","refnum":"??","id":"Definition*-4.2","label":"Definition","title":"","cls":"Definition"},{"reftag":"","neu":true,"reflabel":"Definition","file":"lecture_5","autoid":"Definition*-4.3","refnum":"??","id":"Definition*-4.3","label":"Definition","title":"","cls":"Definition"},{"reftag":"","neu":true,"reflabel":"Theorem","file":"lecture_5","autoid":"Theorem*-4.4","refnum":"??","id":"Theorem*-4.4","label":"Theorem","title":"","cls":"Theorem"},{"reftag":"","neu":true,"reflabel":"Definition","file":"lecture_5","autoid":"Definition*-7.1","refnum":"??","title":"","label":"Definition","id":"Definition*-7.1","cls":"Definition"},{"reftag":"","neu":true,"reflabel":"Theorem","file":"lecture_5","autoid":"Theorem*-7.2","refnum":"??","title":"","label":"Theorem","id":"Theorem*-7.2","cls":"Theorem"}]